{
  "image_key": "hGp3HL6",
  "title": "",
  "caption": "",
  "keywords": [],
  "latitude": "0",
  "longitude": "0",
  "altitude": 0,
  "hidden": false,
  "filename": "NewZealand-8288.jpg",
  "date_time_uploaded": "2014-10-12T21:12:02+00:00",
  "original_height": 3168,
  "original_width": 4752,
  "original_size": 8126297,
  "images": [
    "hGp3HL6-Ti.jpg",
    "hGp3HL6-Th.jpg",
    "hGp3HL6-S.jpg",
    "hGp3HL6-M.jpg",
    "hGp3HL6-L.jpg",
    "hGp3HL6-XL.jpg",
    "hGp3HL6-X2.jpg",
    "hGp3HL6-X3.jpg",
    "hGp3HL6-Original.jpg"
  ]
}