{
  "image_key": "QNkRPhB",
  "title": "",
  "caption": "",
  "keywords": [
    "will kwan",
    "buchan",
    "wilsons cave"
  ],
  "latitude": "0",
  "longitude": "0",
  "altitude": 0,
  "hidden": false,
  "filename": "DSCN4461.JPG",
  "date_time_uploaded": "2006-08-16T00:43:05+00:00",
  "original_height": 1536,
  "original_width": 1840,
  "original_size": 1732332,
  "images": [
    "QNkRPhB-Ti.jpg",
    "QNkRPhB-Th.jpg",
    "QNkRPhB-S.jpg",
    "QNkRPhB-M.jpg",
    "QNkRPhB-L.jpg",
    "QNkRPhB-XL.jpg",
    "QNkRPhB-X2.jpg",
    "QNkRPhB-X3.jpg",
    "QNkRPhB-Original.jpg"
  ],
  "date_time_original": [
    "2006-08-05T23:34:06+00:00"
  ]
}