{
  "image_key": "5qwdDVz",
  "title": "",
  "caption": "",
  "keywords": [
    "Nepal"
  ],
  "latitude": "0",
  "longitude": "0",
  "altitude": 0,
  "hidden": false,
  "filename": "Nepal_20110407_184535_687.jpg",
  "date_time_uploaded": "2011-06-19T16:23:49+00:00",
  "original_height": 2336,
  "original_width": 3504,
  "original_size": 3606839,
  "images": [
    "5qwdDVz-Ti.jpg",
    "5qwdDVz-Th.jpg",
    "5qwdDVz-S.jpg",
    "5qwdDVz-M.jpg",
    "5qwdDVz-L.jpg",
    "5qwdDVz-XL.jpg",
    "5qwdDVz-X2.jpg",
    "5qwdDVz-X3.jpg",
    "5qwdDVz-Original.jpg"
  ],
  "date_time_original": [
    "2011-04-08T01:45:35+00:00"
  ]
}