{
  "image_key": "Jvkhcv4",
  "title": "",
  "caption": "",
  "keywords": [],
  "latitude": "0",
  "longitude": "0",
  "altitude": 0,
  "hidden": false,
  "filename": "61553414.JPG",
  "date_time_uploaded": "2011-06-22T21:01:03+00:00",
  "original_height": 1536,
  "original_width": 2048,
  "original_size": 1375992,
  "images": [
    "Jvkhcv4-Ti.jpg",
    "Jvkhcv4-Th.jpg",
    "Jvkhcv4-S.jpg",
    "Jvkhcv4-M.jpg",
    "Jvkhcv4-L.jpg",
    "Jvkhcv4-XL.jpg",
    "Jvkhcv4-X2.jpg",
    "Jvkhcv4-X3.jpg",
    "Jvkhcv4-Original.jpg"
  ],
  "date_time_original": [
    "2006-03-25T23:22:18+00:00"
  ]
}