{
  "image_key": "T4P4wDL",
  "title": "",
  "caption": "Even out in the wilderness Pete is still addicted to Facebook",
  "keywords": [
    "new zealand",
    "Moke Lake"
  ],
  "latitude": "0",
  "longitude": "0",
  "altitude": 0,
  "hidden": false,
  "filename": "2009_11_23_192907.JPG",
  "date_time_uploaded": "2010-01-28T06:32:19+00:00",
  "original_height": 4863,
  "original_width": 3242,
  "original_size": 8843223,
  "images": [
    "T4P4wDL-Ti.jpg",
    "T4P4wDL-Th.jpg",
    "T4P4wDL-S.jpg",
    "T4P4wDL-M.jpg",
    "T4P4wDL-L.jpg",
    "T4P4wDL-XL.jpg",
    "T4P4wDL-X2.jpg",
    "T4P4wDL-X3.jpg",
    "T4P4wDL-Original.jpg"
  ],
  "date_time_original": [
    "2009-11-24T03:29:07+00:00"
  ]
}