{
  "image_key": "Wn64W2c",
  "title": "",
  "caption": "",
  "keywords": [],
  "latitude": "0",
  "longitude": "0",
  "altitude": 0,
  "hidden": false,
  "filename": "IMG_0191.JPG",
  "date_time_uploaded": "2011-06-22T22:39:33+00:00",
  "original_height": 3168,
  "original_width": 4752,
  "original_size": 6433143,
  "images": [
    "Wn64W2c-Ti.jpg",
    "Wn64W2c-Th.jpg",
    "Wn64W2c-S.jpg",
    "Wn64W2c-M.jpg",
    "Wn64W2c-L.jpg",
    "Wn64W2c-XL.jpg",
    "Wn64W2c-X2.jpg",
    "Wn64W2c-X3.jpg",
    "Wn64W2c-Original.jpg"
  ],
  "date_time_original": [
    "2009-10-08T01:41:01+00:00"
  ]
}