{
  "image_key": "WTf4HGd",
  "title": "",
  "caption": "Rosie, Samantha and Mikey at Squeaky Beach.",
  "keywords": [
    "wilsons prom",
    "squeaky beach",
    "rosie mollison",
    "samantha peverill",
    "mikey harding"
  ],
  "latitude": "-39.024189",
  "longitude": "146.305371",
  "altitude": 0,
  "hidden": false,
  "filename": "Wilsons Prom 085.jpg",
  "date_time_original": "2006-09-17T22:10:25+00:00",
  "date_time_uploaded": "2006-10-07T02:16:06+00:00",
  "original_height": 806,
  "original_width": 1022,
  "original_size": 610233,
  "images": [
    "WTf4HGd-Ti.jpg",
    "WTf4HGd-Th.jpg",
    "WTf4HGd-S.jpg",
    "WTf4HGd-M.jpg",
    "WTf4HGd-L.jpg",
    "WTf4HGd-XL.jpg",
    "WTf4HGd-Original.jpg"
  ]
}