{
  "image_key": "JQ8mSNj",
  "title": "",
  "caption": "",
  "keywords": [
    "snow",
    "skiing",
    "mt stirling"
  ],
  "latitude": "0",
  "longitude": "0",
  "altitude": 0,
  "hidden": false,
  "filename": "173143963.jpg",
  "date_time_uploaded": "2011-06-22T13:40:59+00:00",
  "original_height": 3504,
  "original_width": 2336,
  "original_size": 2147941,
  "images": [
    "JQ8mSNj-Ti.jpg",
    "JQ8mSNj-Th.jpg",
    "JQ8mSNj-S.jpg",
    "JQ8mSNj-M.jpg",
    "JQ8mSNj-L.jpg",
    "JQ8mSNj-XL.jpg",
    "JQ8mSNj-X2.jpg",
    "JQ8mSNj-X3.jpg",
    "JQ8mSNj-Original.jpg"
  ],
  "date_time_original": [
    "2007-07-15T00:10:13+00:00"
  ]
}