{
  "altitude": 0,
  "caption": "",
  "date_time_original": [
    "2007-07-15T19:44:36+00:00"
  ],
  "date_time_uploaded": "2011-06-22T13:16:24+00:00",
  "filename": "173103754_mV36o-O.jpg",
  "hidden": false,
  "image_key": "QWXg2Wf",
  "images": [
    "QWXg2Wf-Ti.jpg",
    "QWXg2Wf-Th.jpg",
    "QWXg2Wf-S.jpg",
    "QWXg2Wf-M.jpg",
    "QWXg2Wf-L.jpg",
    "QWXg2Wf-XL.jpg",
    "QWXg2Wf-X2.jpg",
    "QWXg2Wf-X3.jpg",
    "QWXg2Wf-Original.jpg"
  ],
  "keywords": [],
  "latitude": "0",
  "longitude": "0",
  "original_height": 2048,
  "original_size": 477930,
  "original_width": 1536,
  "title": ""
}
