{
  "image_key": "xZh3Npz",
  "title": "",
  "caption": "Alex strutting his stuff",
  "keywords": [
    "snow",
    "alex cohen",
    "mt stirling",
    "skiing"
  ],
  "latitude": "0",
  "longitude": "0",
  "altitude": 0,
  "hidden": false,
  "filename": "RIMG0035.JPG",
  "date_time_uploaded": "2007-07-27T14:22:17+00:00",
  "original_height": 2112,
  "original_width": 2816,
  "original_size": 2378626,
  "images": [
    "xZh3Npz-Ti.jpg",
    "xZh3Npz-Th.jpg",
    "xZh3Npz-S.jpg",
    "xZh3Npz-M.jpg",
    "xZh3Npz-L.jpg",
    "xZh3Npz-XL.jpg",
    "xZh3Npz-X2.jpg",
    "xZh3Npz-X3.jpg",
    "xZh3Npz-Original.jpg"
  ],
  "date_time_original": [
    "2007-07-15T19:48:17+00:00"
  ]
}