{
  "image_key": "cTQsNwr",
  "title": "",
  "caption": "",
  "keywords": [
    "YouYangs"
  ],
  "latitude": "0",
  "longitude": "0",
  "altitude": 0,
  "hidden": false,
  "filename": "YouYangs_20100516_153723_004.jpg",
  "date_time_uploaded": "2010-06-06T06:27:05+00:00",
  "original_height": 4752,
  "original_width": 3168,
  "original_size": 8034522,
  "images": [
    "cTQsNwr-Ti.jpg",
    "cTQsNwr-Th.jpg",
    "cTQsNwr-S.jpg",
    "cTQsNwr-M.jpg",
    "cTQsNwr-L.jpg",
    "cTQsNwr-XL.jpg",
    "cTQsNwr-X2.jpg",
    "cTQsNwr-X3.jpg",
    "cTQsNwr-Original.jpg"
  ],
  "date_time_original": [
    "2010-05-16T22:37:23+00:00"
  ]
}