{
  "image_key": "RSkJ6qw",
  "title": "",
  "caption": "",
  "keywords": [],
  "latitude": "0",
  "longitude": "0",
  "altitude": 0,
  "hidden": false,
  "filename": "untitled shoot-4885.jpg",
  "date_time_uploaded": "2014-08-08T01:26:17+00:00",
  "original_height": 2831,
  "original_width": 4247,
  "original_size": 7286175,
  "images": [
    "RSkJ6qw-Ti.jpg",
    "RSkJ6qw-Th.jpg",
    "RSkJ6qw-S.jpg",
    "RSkJ6qw-M.jpg",
    "RSkJ6qw-L.jpg",
    "RSkJ6qw-XL.jpg",
    "RSkJ6qw-X2.jpg",
    "RSkJ6qw-X3.jpg",
    "RSkJ6qw-Original.jpg"
  ]
}