{
  "altitude": 0,
  "caption": "",
  "date_time_original": [
    "2006-08-06T20:13:33+00:00"
  ],
  "date_time_uploaded": "2006-08-15T23:51:31+00:00",
  "filename": "DSCN4521.JPG",
  "hidden": false,
  "image_key": "WXgZ8t4",
  "images": [
    "WXgZ8t4-Ti.jpg",
    "WXgZ8t4-Th.jpg",
    "WXgZ8t4-S.jpg",
    "WXgZ8t4-M.jpg",
    "WXgZ8t4-L.jpg",
    "WXgZ8t4-XL.jpg",
    "WXgZ8t4-X2.jpg",
    "WXgZ8t4-X3.jpg",
    "WXgZ8t4-Original.jpg"
  ],
  "keywords": [
    "buchan",
    "honeycomb cave"
  ],
  "latitude": "0",
  "longitude": "0",
  "original_height": 2048,
  "original_size": 1093269,
  "original_width": 1536,
  "title": ""
}
