{
  "image_key": "vBsTQTJ",
  "title": "",
  "caption": "",
  "keywords": [],
  "latitude": "0",
  "longitude": "0",
  "altitude": 0,
  "hidden": false,
  "filename": "IMG_1075.JPG",
  "date_time_uploaded": "2011-06-22T22:19:33+00:00",
  "original_height": 3168,
  "original_width": 4752,
  "original_size": 5438937,
  "images": [
    "vBsTQTJ-Ti.jpg",
    "vBsTQTJ-Th.jpg",
    "vBsTQTJ-S.jpg",
    "vBsTQTJ-M.jpg",
    "vBsTQTJ-L.jpg",
    "vBsTQTJ-XL.jpg",
    "vBsTQTJ-X2.jpg",
    "vBsTQTJ-X3.jpg",
    "vBsTQTJ-Original.jpg"
  ],
  "date_time_original": [
    "2009-11-01T19:06:28+00:00"
  ]
}