{
  "altitude": 0,
  "caption": "",
  "date_time_original": [
    "2009-06-07T23:45:39+00:00"
  ],
  "date_time_uploaded": "2009-07-31T03:00:17+00:00",
  "filename": "RIMG0035.JPG",
  "hidden": false,
  "image_key": "cPtRcjP",
  "images": [
    "cPtRcjP-Ti.jpg",
    "cPtRcjP-Th.jpg",
    "cPtRcjP-S.jpg",
    "cPtRcjP-M.jpg",
    "cPtRcjP-L.jpg",
    "cPtRcjP-XL.jpg",
    "cPtRcjP-X2.jpg",
    "cPtRcjP-X3.jpg",
    "cPtRcjP-Original.jpg"
  ],
  "keywords": [],
  "latitude": "0",
  "longitude": "0",
  "original_height": 2112,
  "original_size": 2288411,
  "original_width": 2816,
  "title": ""
}
