{
  "image_key": "DFVVtGD",
  "title": "",
  "caption": "",
  "keywords": [],
  "latitude": "0",
  "longitude": "0",
  "altitude": 0,
  "hidden": false,
  "filename": "IMG_0950_2.JPG",
  "date_time_uploaded": "2009-11-04T20:17:46+00:00",
  "original_height": 4752,
  "original_width": 3168,
  "original_size": 5123561,
  "images": [
    "DFVVtGD-Ti.jpg",
    "DFVVtGD-Th.jpg",
    "DFVVtGD-S.jpg",
    "DFVVtGD-M.jpg",
    "DFVVtGD-L.jpg",
    "DFVVtGD-XL.jpg",
    "DFVVtGD-X2.jpg",
    "DFVVtGD-X3.jpg",
    "DFVVtGD-Original.jpg"
  ],
  "date_time_original": [
    "2009-10-18T22:34:38+00:00"
  ]
}