{
  "image_key": "R8FXrnD",
  "title": "",
  "caption": "",
  "keywords": [
    "Nepal"
  ],
  "latitude": "0",
  "longitude": "0",
  "altitude": 0,
  "hidden": false,
  "filename": "Nepal_20110329_085821_262.jpg",
  "date_time_uploaded": "2011-06-18T02:33:32+00:00",
  "original_height": 3168,
  "original_width": 4752,
  "original_size": 9668537,
  "images": [
    "R8FXrnD-Ti.jpg",
    "R8FXrnD-Th.jpg",
    "R8FXrnD-S.jpg",
    "R8FXrnD-M.jpg",
    "R8FXrnD-L.jpg",
    "R8FXrnD-XL.jpg",
    "R8FXrnD-X2.jpg",
    "R8FXrnD-X3.jpg",
    "R8FXrnD-Original.jpg"
  ],
  "date_time_original": [
    "2011-03-29T15:58:21+00:00"
  ]
}