{
  "altitude": 0,
  "caption": "",
  "date_time_uploaded": "2014-10-07T03:12:01+00:00",
  "filename": "Zambia-7115.jpg",
  "hidden": false,
  "image_key": "CdLRrph",
  "images": [
    "CdLRrph-Ti.jpg",
    "CdLRrph-Th.jpg",
    "CdLRrph-S.jpg",
    "CdLRrph-M.jpg",
    "CdLRrph-L.jpg",
    "CdLRrph-XL.jpg",
    "CdLRrph-X2.jpg",
    "CdLRrph-X3.jpg",
    "CdLRrph-Original.jpg"
  ],
  "keywords": [],
  "latitude": "0",
  "longitude": "0",
  "original_height": 3168,
  "original_size": 11100176,
  "original_width": 4752,
  "title": ""
}
