{
  "altitude": 0,
  "caption": "",
  "date_time_uploaded": "2014-10-07T03:09:42+00:00",
  "filename": "Zambia-7127.jpg",
  "hidden": false,
  "image_key": "kZK7hwB",
  "images": [
    "kZK7hwB-Ti.jpg",
    "kZK7hwB-Th.jpg",
    "kZK7hwB-S.jpg",
    "kZK7hwB-M.jpg",
    "kZK7hwB-L.jpg",
    "kZK7hwB-XL.jpg",
    "kZK7hwB-X2.jpg",
    "kZK7hwB-X3.jpg",
    "kZK7hwB-Original.jpg"
  ],
  "keywords": [],
  "latitude": "0",
  "longitude": "0",
  "original_height": 3168,
  "original_size": 9543385,
  "original_width": 4752,
  "title": ""
}
