{
  "altitude": 0,
  "caption": "",
  "date_time_uploaded": "2014-10-07T03:44:26+00:00",
  "filename": "Zambia-6413.jpg",
  "hidden": false,
  "image_key": "qZ4vJ8s",
  "images": [
    "qZ4vJ8s-Ti.jpg",
    "qZ4vJ8s-Th.jpg",
    "qZ4vJ8s-S.jpg",
    "qZ4vJ8s-M.jpg",
    "qZ4vJ8s-L.jpg",
    "qZ4vJ8s-XL.jpg",
    "qZ4vJ8s-X2.jpg",
    "qZ4vJ8s-X3.jpg",
    "qZ4vJ8s-Original.jpg"
  ],
  "keywords": [],
  "latitude": "0",
  "longitude": "0",
  "original_height": 3168,
  "original_size": 15534048,
  "original_width": 4752,
  "title": ""
}
