{
  "image_key": "W5R2sPX",
  "title": "",
  "caption": "",
  "keywords": [],
  "latitude": "0",
  "longitude": "0",
  "altitude": 0,
  "hidden": false,
  "filename": "Zambia-6622.jpg",
  "date_time_uploaded": "2014-10-07T03:23:46+00:00",
  "original_height": 3168,
  "original_width": 4752,
  "original_size": 9289240,
  "images": [
    "W5R2sPX-Ti.jpg",
    "W5R2sPX-Th.jpg",
    "W5R2sPX-S.jpg",
    "W5R2sPX-M.jpg",
    "W5R2sPX-L.jpg",
    "W5R2sPX-XL.jpg",
    "W5R2sPX-X2.jpg",
    "W5R2sPX-X3.jpg",
    "W5R2sPX-Original.jpg"
  ]
}