{
  "image_key": "rZBpLwv",
  "title": "",
  "caption": "Pete sits about in Oolite",
  "keywords": [
    "buchan",
    "caving",
    "potholes reserve",
    "peter donald"
  ],
  "latitude": "0",
  "longitude": "0",
  "altitude": 0,
  "hidden": false,
  "filename": "P7060160.JPG",
  "date_time_uploaded": "2011-06-22T12:45:35+00:00",
  "original_height": 3648,
  "original_width": 2736,
  "original_size": 3245019,
  "images": [
    "rZBpLwv-Ti.jpg",
    "rZBpLwv-Th.jpg",
    "rZBpLwv-S.jpg",
    "rZBpLwv-M.jpg",
    "rZBpLwv-L.jpg",
    "rZBpLwv-XL.jpg",
    "rZBpLwv-X2.jpg",
    "rZBpLwv-X3.jpg",
    "rZBpLwv-Original.jpg"
  ],
  "date_time_original": [
    "2008-07-06T19:02:34+00:00"
  ]
}