{
  "node_id": "mWW6g",
  "name": "CragIieburn (15th of November, 2009)",
  "description": "Caragieburn is in between Castle Hill and Arthurs Pass and is where we spent our first night in the van",
  "privacy": "Public",
  "keywords": [],
  "url_name": "CragIieburn-15th-of-November",
  "url_path": "/Travels/New-Zealand-2009/CragIieburn-15th-of-November",
  "date_added": "2010-01-30T08:11:57+00:00",
  "highlight_image_key": "3qFbxzQ",
  "images": [
    "C8QJNKJ",
    "tZPzRD7",
    "JDJvJLd",
    "3qFbxzQ"
  ]
}