{
  "altitude": 0,
  "caption": "",
  "date_time_original": [
    "2010-05-16T22:36:52+00:00"
  ],
  "date_time_uploaded": "2010-06-06T06:24:52+00:00",
  "filename": "YouYangs_20100516_153652_003.jpg",
  "hidden": false,
  "image_key": "Tnx459J",
  "images": [
    "Tnx459J-Ti.jpg",
    "Tnx459J-Th.jpg",
    "Tnx459J-S.jpg",
    "Tnx459J-M.jpg",
    "Tnx459J-L.jpg",
    "Tnx459J-XL.jpg",
    "Tnx459J-X2.jpg",
    "Tnx459J-X3.jpg",
    "Tnx459J-Original.jpg"
  ],
  "keywords": [
    "YouYangs"
  ],
  "latitude": "0",
  "longitude": "0",
  "original_height": 3168,
  "original_size": 7882657,
  "original_width": 4752,
  "title": ""
}
