{
  "image_key": "vxqfvqP",
  "title": "",
  "caption": "",
  "keywords": [
    "YouYangs"
  ],
  "latitude": "0",
  "longitude": "0",
  "altitude": 0,
  "hidden": false,
  "filename": "YouYangs_20100516_145455_001.jpg",
  "date_time_uploaded": "2010-06-06T06:14:56+00:00",
  "original_height": 3168,
  "original_width": 4752,
  "original_size": 11178877,
  "images": [
    "vxqfvqP-Ti.jpg",
    "vxqfvqP-Th.jpg",
    "vxqfvqP-S.jpg",
    "vxqfvqP-M.jpg",
    "vxqfvqP-L.jpg",
    "vxqfvqP-XL.jpg",
    "vxqfvqP-X2.jpg",
    "vxqfvqP-X3.jpg",
    "vxqfvqP-Original.jpg"
  ],
  "date_time_original": [
    "2010-05-16T21:54:55+00:00"
  ]
}