{
  "image_key": "vQSdPBv",
  "title": "",
  "caption": "",
  "keywords": [],
  "latitude": "0",
  "longitude": "0",
  "altitude": 0,
  "hidden": false,
  "filename": "The Kimberley-6318.jpg",
  "date_time_uploaded": "2013-08-11T03:44:54+00:00",
  "original_height": 3168,
  "original_width": 4752,
  "original_size": 16311439,
  "images": [
    "vQSdPBv-Ti.jpg",
    "vQSdPBv-Th.jpg",
    "vQSdPBv-S.jpg",
    "vQSdPBv-M.jpg",
    "vQSdPBv-L.jpg",
    "vQSdPBv-XL.jpg",
    "vQSdPBv-X2.jpg",
    "vQSdPBv-X3.jpg",
    "vQSdPBv-Original.jpg"
  ]
}