{
  "altitude": 0,
  "caption": "",
  "date_time_original": [
    "2007-09-26T23:46:56+00:00"
  ],
  "date_time_uploaded": "2008-05-18T04:25:57+00:00",
  "filename": "217429248.jpg",
  "hidden": false,
  "image_key": "DTxDgZz",
  "images": [
    "DTxDgZz-Ti.jpg",
    "DTxDgZz-Th.jpg",
    "DTxDgZz-S.jpg",
    "DTxDgZz-M.jpg",
    "DTxDgZz-L.jpg",
    "DTxDgZz-XL.jpg",
    "DTxDgZz-X2.jpg",
    "DTxDgZz-X3.jpg",
    "DTxDgZz-Original.jpg"
  ],
  "keywords": [
    "mt arapiles",
    "climbing",
    "josefin blondell"
  ],
  "latitude": "0",
  "longitude": "0",
  "original_height": 2816,
  "original_size": 2329496,
  "original_width": 2112,
  "title": ""
}
