{
  "altitude": 0,
  "caption": "",
  "date_time_original": [
    "2011-03-25T16:33:56+00:00"
  ],
  "date_time_uploaded": "2011-06-17T23:21:12+00:00",
  "filename": "Nepal_20110325_093356_165.jpg",
  "hidden": false,
  "image_key": "9KSg23F",
  "images": [
    "9KSg23F-Ti.jpg",
    "9KSg23F-Th.jpg",
    "9KSg23F-S.jpg",
    "9KSg23F-M.jpg",
    "9KSg23F-L.jpg",
    "9KSg23F-XL.jpg",
    "9KSg23F-X2.jpg",
    "9KSg23F-X3.jpg",
    "9KSg23F-Original.jpg"
  ],
  "keywords": [
    "Nepal"
  ],
  "latitude": "0",
  "longitude": "0",
  "original_height": 4752,
  "original_size": 7734185,
  "original_width": 3168,
  "title": ""
}
