{
  "altitude": 0,
  "caption": "",
  "date_time_original": [
    "2011-03-30T18:03:07+00:00"
  ],
  "date_time_uploaded": "2011-06-18T06:00:32+00:00",
  "filename": "Nepal_20110330_110307_392.jpg",
  "hidden": false,
  "image_key": "kMHcDZM",
  "images": [
    "kMHcDZM-Ti.jpg",
    "kMHcDZM-Th.jpg",
    "kMHcDZM-S.jpg",
    "kMHcDZM-M.jpg",
    "kMHcDZM-L.jpg",
    "kMHcDZM-XL.jpg",
    "kMHcDZM-X2.jpg",
    "kMHcDZM-X3.jpg",
    "kMHcDZM-Original.jpg"
  ],
  "keywords": [
    "Nepal"
  ],
  "latitude": "0",
  "longitude": "0",
  "original_height": 2336,
  "original_size": 4371953,
  "original_width": 3504,
  "title": ""
}
