{
  "altitude": 0,
  "caption": "",
  "date_time_original": [
    "2009-12-08T18:37:34+00:00"
  ],
  "date_time_uploaded": "2009-12-30T18:39:15+00:00",
  "filename": "2009_12_08_103734.JPG",
  "hidden": false,
  "image_key": "ddC3BB8",
  "images": [
    "ddC3BB8-Ti.jpg",
    "ddC3BB8-Th.jpg",
    "ddC3BB8-S.jpg",
    "ddC3BB8-M.jpg",
    "ddC3BB8-L.jpg",
    "ddC3BB8-XL.jpg",
    "ddC3BB8-X2.jpg",
    "ddC3BB8-X3.jpg",
    "ddC3BB8-Original.jpg"
  ],
  "keywords": [
    "new zealand",
    "abel tasman",
    "peter donald"
  ],
  "latitude": "0",
  "longitude": "0",
  "original_height": 3145,
  "original_size": 9225017,
  "original_width": 4718,
  "title": ""
}
