{
  "altitude": 0,
  "caption": "",
  "date_time_original": [
    "2012-08-06T09:13:12+00:00"
  ],
  "date_time_uploaded": "2012-10-24T01:28:51+00:00",
  "filename": "20120806_021312_3279.jpg",
  "hidden": false,
  "image_key": "2j7gWsP",
  "images": [
    "2j7gWsP-Ti.jpg",
    "2j7gWsP-Th.jpg",
    "2j7gWsP-S.jpg",
    "2j7gWsP-M.jpg",
    "2j7gWsP-L.jpg",
    "2j7gWsP-XL.jpg",
    "2j7gWsP-X2.jpg",
    "2j7gWsP-X3.jpg",
    "2j7gWsP-Original.jpg"
  ],
  "keywords": [],
  "latitude": "0",
  "longitude": "0",
  "original_height": 3112,
  "original_size": 10394697,
  "original_width": 4668,
  "title": ""
}
