{
  "altitude": 0,
  "caption": "Rob coming up the second pitch of Dracula",
  "date_time_original": [
    "2008-04-20T21:44:28+00:00"
  ],
  "date_time_uploaded": "2008-05-18T06:00:44+00:00",
  "filename": "IMG_7171.JPG",
  "hidden": false,
  "image_key": "MWCTkMw",
  "images": [
    "MWCTkMw-Ti.jpg",
    "MWCTkMw-Th.jpg",
    "MWCTkMw-S.jpg",
    "MWCTkMw-M.jpg",
    "MWCTkMw-L.jpg",
    "MWCTkMw-XL.jpg",
    "MWCTkMw-X2.jpg",
    "MWCTkMw-X3.jpg",
    "MWCTkMw-Original.jpg"
  ],
  "keywords": [
    "mt arapiles",
    "climbing",
    "rob west",
    "hilary cox"
  ],
  "latitude": "0",
  "longitude": "0",
  "original_height": 1200,
  "original_size": 624656,
  "original_width": 1600,
  "title": ""
}
