{
  "altitude": 0,
  "caption": "More flowers",
  "date_time_original": [
    "2009-12-02T05:00:06+00:00"
  ],
  "date_time_uploaded": "2010-01-28T06:40:08+00:00",
  "filename": "2009_12_01_210006.JPG",
  "hidden": false,
  "image_key": "W3fdc6V",
  "images": [
    "W3fdc6V-Ti.jpg",
    "W3fdc6V-Th.jpg",
    "W3fdc6V-S.jpg",
    "W3fdc6V-M.jpg",
    "W3fdc6V-L.jpg",
    "W3fdc6V-XL.jpg",
    "W3fdc6V-X2.jpg",
    "W3fdc6V-X3.jpg",
    "W3fdc6V-Original.jpg"
  ],
  "keywords": [
    "Ahuriri",
    "Bridge",
    "new zealand"
  ],
  "latitude": "0",
  "longitude": "0",
  "original_height": 3130,
  "original_size": 9851806,
  "original_width": 4695,
  "title": ""
}
