{
  "altitude": 0,
  "caption": "",
  "date_time_original": [
    "2011-04-06T18:11:38+00:00"
  ],
  "date_time_uploaded": "2011-06-19T13:31:32+00:00",
  "filename": "Nepal_20110406_111138_572.jpg",
  "hidden": false,
  "image_key": "KzJVRpm",
  "images": [
    "KzJVRpm-Ti.jpg",
    "KzJVRpm-Th.jpg",
    "KzJVRpm-S.jpg",
    "KzJVRpm-M.jpg",
    "KzJVRpm-L.jpg",
    "KzJVRpm-XL.jpg",
    "KzJVRpm-X2.jpg",
    "KzJVRpm-X3.jpg",
    "KzJVRpm-Original.jpg"
  ],
  "keywords": [
    "Nepal"
  ],
  "latitude": "0",
  "longitude": "0",
  "original_height": 4752,
  "original_size": 9756403,
  "original_width": 3168,
  "title": ""
}
