{
  "altitude": 0,
  "caption": "",
  "date_time_original": [
    "2011-04-05T19:42:12+00:00"
  ],
  "date_time_uploaded": "2011-06-19T12:44:41+00:00",
  "filename": "Nepal_20110405_124212_553.jpg",
  "hidden": false,
  "image_key": "pK3v9DM",
  "images": [
    "pK3v9DM-Ti.jpg",
    "pK3v9DM-Th.jpg",
    "pK3v9DM-S.jpg",
    "pK3v9DM-M.jpg",
    "pK3v9DM-L.jpg",
    "pK3v9DM-XL.jpg",
    "pK3v9DM-X2.jpg",
    "pK3v9DM-X3.jpg",
    "pK3v9DM-Original.jpg"
  ],
  "keywords": [
    "Nepal"
  ],
  "latitude": "0",
  "longitude": "0",
  "original_height": 3168,
  "original_size": 7970240,
  "original_width": 4752,
  "title": ""
}
