{
  "altitude": 0,
  "caption": "",
  "date_time_original": [
    "2011-04-06T18:54:06+00:00"
  ],
  "date_time_uploaded": "2011-06-19T13:56:03+00:00",
  "filename": "Nepal_20110406_115406_585.jpg",
  "hidden": false,
  "image_key": "xF6qXGW",
  "images": [
    "xF6qXGW-Ti.jpg",
    "xF6qXGW-Th.jpg",
    "xF6qXGW-S.jpg",
    "xF6qXGW-M.jpg",
    "xF6qXGW-L.jpg",
    "xF6qXGW-XL.jpg",
    "xF6qXGW-X2.jpg",
    "xF6qXGW-X3.jpg",
    "xF6qXGW-Original.jpg"
  ],
  "keywords": [
    "Nepal"
  ],
  "latitude": "0",
  "longitude": "0",
  "original_height": 2336,
  "original_size": 3810957,
  "original_width": 3504,
  "title": ""
}
