{
  "altitude": 0,
  "caption": "Krisy presenting for a photo",
  "date_time_original": [
    "2006-06-18T02:46:07+00:00"
  ],
  "date_time_uploaded": "2006-06-30T06:46:16+00:00",
  "filename": "IMG_3171.jpg",
  "hidden": false,
  "image_key": "w9HDFrg",
  "images": [
    "w9HDFrg-Ti.jpg",
    "w9HDFrg-Th.jpg",
    "w9HDFrg-S.jpg",
    "w9HDFrg-M.jpg",
    "w9HDFrg-L.jpg",
    "w9HDFrg-XL.jpg",
    "w9HDFrg-X2.jpg",
    "w9HDFrg-X3.jpg",
    "w9HDFrg-Original.jpg"
  ],
  "keywords": [
    "krisy moore",
    "new zealand",
    "franz joseph"
  ],
  "latitude": "0",
  "longitude": "0",
  "original_height": 2592,
  "original_size": 1607084,
  "original_width": 1944,
  "title": ""
}
