{
  "image_key": "RHK6MmG",
  "title": "",
  "caption": "",
  "keywords": [
    "new zealand"
  ],
  "latitude": "0",
  "longitude": "0",
  "altitude": 0,
  "hidden": false,
  "filename": "P1020612.JPG",
  "date_time_uploaded": "2009-12-27T10:13:07+00:00",
  "original_height": 800,
  "original_width": 570,
  "original_size": 155378,
  "images": [
    "RHK6MmG-Ti.jpg",
    "RHK6MmG-Th.jpg",
    "RHK6MmG-S.jpg",
    "RHK6MmG-M.jpg",
    "RHK6MmG-L.jpg",
    "RHK6MmG-XL.jpg",
    "RHK6MmG-Original.jpg"
  ]
}