{
  "altitude": 0,
  "caption": "",
  "date_time_uploaded": "2010-02-10T13:43:57+00:00",
  "filename": "websiteScreenshot_lifestyle1-780x522.jpg",
  "hidden": false,
  "image_key": "nV37t5Q",
  "images": [
    "nV37t5Q-Ti.jpg",
    "nV37t5Q-Th.jpg",
    "nV37t5Q-S.jpg",
    "nV37t5Q-M.jpg",
    "nV37t5Q-Original.jpg"
  ],
  "keywords": [
    "websiteScreenshot",
    "lifestyle1",
    "780x522"
  ],
  "latitude": "0",
  "longitude": "0",
  "original_height": 522,
  "original_size": 108798,
  "original_width": 780,
  "title": ""
}
