{
  "image_key": "ChtB3DN",
  "title": "",
  "caption": "",
  "keywords": [
    "Nepal"
  ],
  "latitude": "0",
  "longitude": "0",
  "altitude": 0,
  "hidden": false,
  "filename": "Nepal_20110322_121037_100.jpg",
  "date_time_uploaded": "2011-06-17T19:39:17+00:00",
  "original_height": 4752,
  "original_width": 3168,
  "original_size": 10271585,
  "images": [
    "ChtB3DN-Ti.jpg",
    "ChtB3DN-Th.jpg",
    "ChtB3DN-S.jpg",
    "ChtB3DN-M.jpg",
    "ChtB3DN-L.jpg",
    "ChtB3DN-XL.jpg",
    "ChtB3DN-X2.jpg",
    "ChtB3DN-X3.jpg",
    "ChtB3DN-Original.jpg"
  ],
  "date_time_original": [
    "2011-03-22T19:10:37+00:00"
  ]
}