{
  "altitude": 0,
  "caption": "",
  "date_time_uploaded": "2014-10-06T23:09:25+00:00",
  "filename": "Zambia-7600.jpg",
  "hidden": false,
  "image_key": "hdsFrMG",
  "images": [
    "hdsFrMG-Ti.jpg",
    "hdsFrMG-Th.jpg",
    "hdsFrMG-S.jpg",
    "hdsFrMG-M.jpg",
    "hdsFrMG-L.jpg",
    "hdsFrMG-XL.jpg",
    "hdsFrMG-X2.jpg",
    "hdsFrMG-X3.jpg",
    "hdsFrMG-Original.jpg"
  ],
  "keywords": [],
  "latitude": "0",
  "longitude": "0",
  "original_height": 3168,
  "original_size": 9132969,
  "original_width": 4752,
  "title": ""
}
