{
  "altitude": 0,
  "caption": "",
  "date_time_uploaded": "2014-10-07T00:17:07+00:00",
  "filename": "Zambia-7546.jpg",
  "hidden": false,
  "image_key": "TgZxjQD",
  "images": [
    "TgZxjQD-Ti.jpg",
    "TgZxjQD-Th.jpg",
    "TgZxjQD-S.jpg",
    "TgZxjQD-M.jpg",
    "TgZxjQD-L.jpg",
    "TgZxjQD-XL.jpg",
    "TgZxjQD-X2.jpg",
    "TgZxjQD-X3.jpg",
    "TgZxjQD-Original.jpg"
  ],
  "keywords": [],
  "latitude": "0",
  "longitude": "0",
  "original_height": 4752,
  "original_size": 9681744,
  "original_width": 3168,
  "title": ""
}
