{
  "altitude": 0,
  "caption": "",
  "date_time_original": [
    "2011-04-04T17:36:17+00:00"
  ],
  "date_time_uploaded": "2011-06-19T11:35:47+00:00",
  "filename": "Nepal_20110404_103617_512.jpg",
  "hidden": false,
  "image_key": "CdZjqLJ",
  "images": [
    "CdZjqLJ-Ti.jpg",
    "CdZjqLJ-Th.jpg",
    "CdZjqLJ-S.jpg",
    "CdZjqLJ-M.jpg",
    "CdZjqLJ-L.jpg",
    "CdZjqLJ-XL.jpg",
    "CdZjqLJ-X2.jpg",
    "CdZjqLJ-X3.jpg",
    "CdZjqLJ-Original.jpg"
  ],
  "keywords": [
    "Nepal"
  ],
  "latitude": "0",
  "longitude": "0",
  "original_height": 3504,
  "original_size": 5908082,
  "original_width": 2336,
  "title": ""
}
