{
  "image_key": "st7vKcG",
  "title": "",
  "caption": "",
  "keywords": [
    "Nepal"
  ],
  "latitude": "0",
  "longitude": "0",
  "altitude": 0,
  "hidden": false,
  "filename": "Nepal_20110404_101143_509.jpg",
  "date_time_uploaded": "2011-06-19T11:31:05+00:00",
  "original_height": 4752,
  "original_width": 3168,
  "original_size": 9574369,
  "images": [
    "st7vKcG-Ti.jpg",
    "st7vKcG-Th.jpg",
    "st7vKcG-S.jpg",
    "st7vKcG-M.jpg",
    "st7vKcG-L.jpg",
    "st7vKcG-XL.jpg",
    "st7vKcG-X2.jpg",
    "st7vKcG-X3.jpg",
    "st7vKcG-Original.jpg"
  ],
  "date_time_original": [
    "2011-04-04T17:11:43+00:00"
  ]
}