{
  "altitude": 0,
  "caption": "",
  "date_time_original": [
    "2006-11-09T20:40:49+00:00"
  ],
  "date_time_uploaded": "2006-11-12T07:45:24+00:00",
  "filename": "Richmond 003.jpg",
  "hidden": false,
  "image_key": "XjNBs3J",
  "images": [
    "XjNBs3J-Ti.jpg",
    "XjNBs3J-Th.jpg",
    "XjNBs3J-S.jpg",
    "XjNBs3J-M.jpg",
    "XjNBs3J-L.jpg",
    "XjNBs3J-XL.jpg",
    "XjNBs3J-X2.jpg",
    "XjNBs3J-X3.jpg",
    "XjNBs3J-Original.jpg"
  ],
  "keywords": [
    "fixme"
  ],
  "latitude": "-37.8201611111",
  "longitude": "145.007833333",
  "original_height": 2112,
  "original_size": 2318723,
  "original_width": 2816,
  "title": ""
}
