{
  "image_key": "mqhvZsT",
  "title": "",
  "caption": "Looking out from where we climbed",
  "keywords": [
    "cathedral ranges"
  ],
  "latitude": "0",
  "longitude": "0",
  "altitude": 0,
  "hidden": false,
  "filename": "37.jpg",
  "date_time_uploaded": "2006-06-28T01:45:17+00:00",
  "original_height": 1200,
  "original_width": 1600,
  "original_size": 968111,
  "images": [
    "mqhvZsT-Ti.jpg",
    "mqhvZsT-Th.jpg",
    "mqhvZsT-S.jpg",
    "mqhvZsT-M.jpg",
    "mqhvZsT-L.jpg",
    "mqhvZsT-XL.jpg",
    "mqhvZsT-X2.jpg",
    "mqhvZsT-X3.jpg",
    "mqhvZsT-Original.jpg"
  ],
  "date_time_original": [
    "2006-03-19T18:10:42+00:00"
  ]
}