{
  "image_key": "rSRh42M",
  "title": "",
  "caption": "Krisy and Chris",
  "keywords": [
    "krisy moore",
    "chris bull",
    "cathedral ranges"
  ],
  "latitude": "0",
  "longitude": "0",
  "altitude": 0,
  "hidden": false,
  "filename": "34.jpg",
  "date_time_uploaded": "2006-06-28T01:41:08+00:00",
  "original_height": 1920,
  "original_width": 2560,
  "original_size": 808897,
  "images": [
    "rSRh42M-Ti.jpg",
    "rSRh42M-Th.jpg",
    "rSRh42M-S.jpg",
    "rSRh42M-M.jpg",
    "rSRh42M-L.jpg",
    "rSRh42M-XL.jpg",
    "rSRh42M-X2.jpg",
    "rSRh42M-X3.jpg",
    "rSRh42M-Original.jpg"
  ],
  "date_time_original": [
    "2006-03-19T03:03:22+00:00"
  ]
}