{
  "image_key": "sgRznLd",
  "title": "",
  "caption": "",
  "keywords": [],
  "latitude": "0",
  "longitude": "0",
  "altitude": 0,
  "hidden": false,
  "filename": "untitled shoot-0322.jpg",
  "date_time_uploaded": "2015-08-09T10:43:40+00:00",
  "original_height": 3264,
  "original_width": 2448,
  "original_size": 6362108,
  "images": [
    "sgRznLd-Ti.jpg",
    "sgRznLd-Th.jpg",
    "sgRznLd-S.jpg",
    "sgRznLd-M.jpg",
    "sgRznLd-L.jpg",
    "sgRznLd-XL.jpg",
    "sgRznLd-X2.jpg",
    "sgRznLd-X3.jpg",
    "sgRznLd-Original.jpg"
  ]
}