{
  "altitude": 0,
  "caption": "",
  "date_time_uploaded": "2015-08-09T11:06:40+00:00",
  "filename": "untitled shoot-0278.jpg",
  "hidden": false,
  "image_key": "wszw2KH",
  "images": [
    "wszw2KH-Ti.jpg",
    "wszw2KH-Th.jpg",
    "wszw2KH-S.jpg",
    "wszw2KH-M.jpg",
    "wszw2KH-L.jpg",
    "wszw2KH-XL.jpg",
    "wszw2KH-X2.jpg",
    "wszw2KH-X3.jpg",
    "wszw2KH-Original.jpg"
  ],
  "keywords": [],
  "latitude": "0",
  "longitude": "0",
  "original_height": 3264,
  "original_size": 5905011,
  "original_width": 2448,
  "title": ""
}
