{
  "altitude": 0,
  "caption": "",
  "date_time_original": [
    "2007-08-25T23:14:16+00:00"
  ],
  "date_time_uploaded": "2007-09-30T22:07:34+00:00",
  "filename": "DSC_4091.JPG",
  "hidden": false,
  "image_key": "kZxxvF9",
  "images": [
    "kZxxvF9-Ti.jpg",
    "kZxxvF9-Th.jpg",
    "kZxxvF9-S.jpg",
    "kZxxvF9-M.jpg",
    "kZxxvF9-L.jpg",
    "kZxxvF9-XL.jpg",
    "kZxxvF9-X2.jpg",
    "kZxxvF9-X3.jpg",
    "kZxxvF9-Original.jpg"
  ],
  "keywords": [
    "buchan",
    "ying ying",
    "pot holes reserve"
  ],
  "latitude": "0",
  "longitude": "0",
  "original_height": 2592,
  "original_size": 4808024,
  "original_width": 3872,
  "title": ""
}
