{
  "node_id": "kbv8H",
  "name": "Mt Arapiles (12th of February, 2011)",
  "description": "",
  "privacy": "Public",
  "keywords": [],
  "url_name": "Mt-Arapiles-12th-of-February",
  "url_path": "/Climbing/Arapiles/Mt-Arapiles-12th-of-February",
  "date_added": "2011-04-15T14:48:09+00:00",
  "highlight_image_uri": "/api/v2/highlight/node/kbv8H",
  "images": [
    "cbGWmzK",
    "FW2S6nx",
    "F2NHmpZ",
    "RbLqJtC",
    "BnGPMBV",
    "WR2dkZ3",
    "qSBhn5g",
    "Z8pPkJh",
    "fHS2Mmt"
  ]
}