{
  "altitude": 0,
  "caption": "Kim gets bored and climbs a tree",
  "date_time_original": [
    "2009-05-23T18:52:06+00:00"
  ],
  "date_time_uploaded": "2009-05-29T13:10:35+00:00",
  "filename": "RIMG0023.JPG",
  "hidden": false,
  "image_key": "2GzHqGZ",
  "images": [
    "2GzHqGZ-Ti.jpg",
    "2GzHqGZ-Th.jpg",
    "2GzHqGZ-S.jpg",
    "2GzHqGZ-M.jpg",
    "2GzHqGZ-L.jpg",
    "2GzHqGZ-XL.jpg",
    "2GzHqGZ-X2.jpg",
    "2GzHqGZ-X3.jpg",
    "2GzHqGZ-Original.jpg"
  ],
  "keywords": [
    "Araps Base Camp",
    "kim bagot"
  ],
  "latitude": "0",
  "longitude": "0",
  "original_height": 2816,
  "original_size": 3432013,
  "original_width": 2112,
  "title": ""
}
