{
  "altitude": 0,
  "caption": "",
  "date_time_uploaded": "2013-08-12T01:35:29+00:00",
  "filename": "untitled shoot-6172.jpg",
  "hidden": false,
  "image_key": "NQdTnqX",
  "images": [
    "NQdTnqX-Ti.jpg",
    "NQdTnqX-Th.jpg",
    "NQdTnqX-S.jpg",
    "NQdTnqX-M.jpg",
    "NQdTnqX-L.jpg",
    "NQdTnqX-XL.jpg",
    "NQdTnqX-X2.jpg",
    "NQdTnqX-X3.jpg",
    "NQdTnqX-Original.jpg"
  ],
  "keywords": [],
  "latitude": "0",
  "longitude": "0",
  "original_height": 4752,
  "original_size": 12529951,
  "original_width": 3168,
  "title": ""
}
