{
  "altitude": 0,
  "caption": "Directly behind the wall.",
  "date_time_original": [
    "2006-08-12T20:28:38+00:00"
  ],
  "date_time_uploaded": "2006-08-14T08:36:31+00:00",
  "filename": "Climbing 011.jpg",
  "hidden": false,
  "image_key": "8zf7GHw",
  "images": [
    "8zf7GHw-Ti.jpg",
    "8zf7GHw-Th.jpg",
    "8zf7GHw-S.jpg",
    "8zf7GHw-M.jpg",
    "8zf7GHw-L.jpg",
    "8zf7GHw-XL.jpg",
    "8zf7GHw-X2.jpg",
    "8zf7GHw-Original.jpg"
  ],
  "keywords": [
    "werribee gorge"
  ],
  "latitude": "0",
  "longitude": "0",
  "original_height": 960,
  "original_size": 779646,
  "original_width": 1280,
  "title": ""
}
