{
  "date_added": "1970-01-01T00:00:00+00:00",
  "description": "Miscellaneous pictures from New Zealand that did not fit anywhere else.",
  "highlight_image_key": "gcn4mwQ",
  "images": [
    "6Sp2MCm",
    "82JqZ9K",
    "gcn4mwQ",
    "wBHLfNq",
    "GcH39zk",
    "5Skb79N",
    "PMm26V7",
    "tJFfXFk",
    "tK2kRMJ",
    "nZvGmW8",
    "Gd5zZhH",
    "GqHZjGP",
    "fmNJSJB",
    "j73hGzg",
    "Lp8zrBR",
    "ZzQcgJq",
    "jN2W7nC"
  ],
  "keywords": [],
  "name": "Misc New Zealand Pictures",
  "node_id": "57ssX",
  "privacy": "Public",
  "url_name": "Misc-New-Zealand-Pictures",
  "url_path": "/Travels/New-Zealand-2006/Misc-New-Zealand-Pictures"
}
