{
  "node_id": "7mKSx9",
  "name": "The Kimberley 2015",
  "description": "We spent just over a month in the Kimberley where I got to be a house dad and Sally returned to the work she loves.",
  "privacy": "Public",
  "keywords": [],
  "url_name": "The-Kimberley-2015",
  "url_path": "/Travels/The-Kimberley-2015",
  "date_added": "2015-08-11T00:29:23+00:00",
  "highlight_image_key": "kBkbgHG",
  "child_nodes": [
    "Fitzroy-Crossing",
    "Derby-Wharf",
    "Mowanjum-Festival",
    "Bush-Poets-Breakfast"
  ]
}