{
  "altitude": 0,
  "caption": "",
  "date_time_uploaded": "2014-09-28T23:39:24+00:00",
  "filename": "Zambia-7628.jpg",
  "hidden": false,
  "image_key": "BdKVxhM",
  "images": [
    "BdKVxhM-Ti.jpg",
    "BdKVxhM-Th.jpg",
    "BdKVxhM-S.jpg",
    "BdKVxhM-M.jpg",
    "BdKVxhM-L.jpg",
    "BdKVxhM-XL.jpg",
    "BdKVxhM-X2.jpg",
    "BdKVxhM-X3.jpg",
    "BdKVxhM-Original.jpg"
  ],
  "keywords": [],
  "latitude": "0",
  "longitude": "0",
  "original_height": 4752,
  "original_size": 11277904,
  "original_width": 3168,
  "title": ""
}
