{
  "altitude": 0,
  "caption": "",
  "date_time_uploaded": "2014-09-28T23:35:04+00:00",
  "filename": "Zambia-7675.jpg",
  "hidden": false,
  "image_key": "KpqXbjn",
  "images": [
    "KpqXbjn-Ti.jpg",
    "KpqXbjn-Th.jpg",
    "KpqXbjn-S.jpg",
    "KpqXbjn-M.jpg",
    "KpqXbjn-L.jpg",
    "KpqXbjn-XL.jpg",
    "KpqXbjn-X2.jpg",
    "KpqXbjn-X3.jpg",
    "KpqXbjn-Original.jpg"
  ],
  "keywords": [],
  "latitude": "0",
  "longitude": "0",
  "original_height": 2968,
  "original_size": 7589792,
  "original_width": 4452,
  "title": ""
}
