{
  "image_key": "MCrw7jn",
  "title": "",
  "caption": "Visiting our guides home, just outside Kathmandu",
  "keywords": [],
  "latitude": "0",
  "longitude": "0",
  "altitude": 0,
  "hidden": false,
  "filename": "untitled shoot-4609.jpg",
  "date_time_uploaded": "2014-02-10T06:13:06+00:00",
  "original_height": 3168,
  "original_width": 4752,
  "original_size": 8836551,
  "images": [
    "MCrw7jn-Ti.jpg",
    "MCrw7jn-Th.jpg",
    "MCrw7jn-S.jpg",
    "MCrw7jn-M.jpg",
    "MCrw7jn-L.jpg",
    "MCrw7jn-XL.jpg",
    "MCrw7jn-X2.jpg",
    "MCrw7jn-X3.jpg",
    "MCrw7jn-Original.jpg"
  ]
}