{
  "altitude": 0,
  "caption": "",
  "date_time_original": [
    "2006-06-19T21:22:43+00:00"
  ],
  "date_time_uploaded": "2006-06-30T06:03:19+00:00",
  "filename": "Stuart 075.jpg",
  "hidden": false,
  "image_key": "TJ66RbC",
  "images": [
    "TJ66RbC-Ti.jpg",
    "TJ66RbC-Th.jpg",
    "TJ66RbC-S.jpg",
    "TJ66RbC-M.jpg",
    "TJ66RbC-L.jpg",
    "TJ66RbC-XL.jpg",
    "TJ66RbC-X2.jpg",
    "TJ66RbC-X3.jpg",
    "TJ66RbC-Original.jpg"
  ],
  "keywords": [
    "new zealand"
  ],
  "latitude": "0",
  "longitude": "0",
  "original_height": 2304,
  "original_size": 2241395,
  "original_width": 3456,
  "title": ""
}
