{
  "altitude": 0,
  "caption": "",
  "date_time_uploaded": "2014-01-11T03:11:21+00:00",
  "filename": "Zambia-7223.jpg",
  "hidden": false,
  "image_key": "KmsLZgh",
  "images": [
    "KmsLZgh-Ti.jpg",
    "KmsLZgh-Th.jpg",
    "KmsLZgh-S.jpg",
    "KmsLZgh-M.jpg",
    "KmsLZgh-L.jpg",
    "KmsLZgh-XL.jpg",
    "KmsLZgh-X2.jpg",
    "KmsLZgh-X3.jpg",
    "KmsLZgh-Original.jpg"
  ],
  "keywords": [],
  "latitude": "0",
  "longitude": "0",
  "original_height": 4752,
  "original_size": 8295090,
  "original_width": 3168,
  "title": ""
}
