{
  "image_key": "PRnzV84",
  "title": "",
  "caption": "",
  "keywords": [],
  "latitude": "0",
  "longitude": "0",
  "altitude": 0,
  "hidden": false,
  "filename": "Zambia-7212.jpg",
  "date_time_uploaded": "2014-01-11T03:01:29+00:00",
  "original_height": 4473,
  "original_width": 2982,
  "original_size": 6072242,
  "images": [
    "PRnzV84-Ti.jpg",
    "PRnzV84-Th.jpg",
    "PRnzV84-S.jpg",
    "PRnzV84-M.jpg",
    "PRnzV84-L.jpg",
    "PRnzV84-XL.jpg",
    "PRnzV84-X2.jpg",
    "PRnzV84-X3.jpg",
    "PRnzV84-Original.jpg"
  ]
}