{
  "altitude": 0,
  "caption": "",
  "date_time_uploaded": "2014-01-11T03:48:45+00:00",
  "filename": "Zambia-7236.jpg",
  "hidden": false,
  "image_key": "tM6TVws",
  "images": [
    "tM6TVws-Ti.jpg",
    "tM6TVws-Th.jpg",
    "tM6TVws-S.jpg",
    "tM6TVws-M.jpg",
    "tM6TVws-L.jpg",
    "tM6TVws-XL.jpg",
    "tM6TVws-X2.jpg",
    "tM6TVws-X3.jpg",
    "tM6TVws-Original.jpg"
  ],
  "keywords": [],
  "latitude": "0",
  "longitude": "0",
  "original_height": 3168,
  "original_size": 7442707,
  "original_width": 4752,
  "title": ""
}
