{
  "altitude": 0,
  "caption": "",
  "date_time_uploaded": "2014-10-07T05:53:30+00:00",
  "filename": "Zambia-6931.jpg",
  "hidden": false,
  "image_key": "xMKVbB2",
  "images": [
    "xMKVbB2-Ti.jpg",
    "xMKVbB2-Th.jpg",
    "xMKVbB2-S.jpg",
    "xMKVbB2-M.jpg",
    "xMKVbB2-L.jpg",
    "xMKVbB2-XL.jpg",
    "xMKVbB2-X2.jpg",
    "xMKVbB2-X3.jpg",
    "xMKVbB2-Original.jpg"
  ],
  "keywords": [],
  "latitude": "0",
  "longitude": "0",
  "original_height": 3168,
  "original_size": 12204865,
  "original_width": 4752,
  "title": ""
}
