{
  "altitude": 0,
  "caption": "The duck",
  "date_time_original": [
    "2006-06-15T18:03:56+00:00"
  ],
  "date_time_uploaded": "2006-06-30T01:29:44+00:00",
  "filename": "Stuart 057.jpg",
  "hidden": false,
  "image_key": "JBpmPVn",
  "images": [
    "JBpmPVn-Ti.jpg",
    "JBpmPVn-Th.jpg",
    "JBpmPVn-S.jpg",
    "JBpmPVn-M.jpg",
    "JBpmPVn-L.jpg",
    "JBpmPVn-XL.jpg",
    "JBpmPVn-X2.jpg",
    "JBpmPVn-X3.jpg",
    "JBpmPVn-Original.jpg"
  ],
  "keywords": [
    "new zealand",
    "nelson lakes national park"
  ],
  "latitude": "0",
  "longitude": "0",
  "original_height": 2304,
  "original_size": 2417586,
  "original_width": 3456,
  "title": ""
}
