{
  "altitude": 0,
  "caption": "",
  "date_time_original": [
    "2008-05-03T14:28:53+00:00"
  ],
  "date_time_uploaded": "2008-05-06T02:10:00+00:00",
  "filename": "WombatState2.JPG",
  "hidden": false,
  "image_key": "575ffN7",
  "images": [
    "575ffN7-Ti.jpg",
    "575ffN7-Th.jpg",
    "575ffN7-S.jpg",
    "575ffN7-M.jpg",
    "575ffN7-L.jpg",
    "575ffN7-XL.jpg",
    "575ffN7-X2.jpg",
    "575ffN7-X3.jpg",
    "575ffN7-Original.jpg"
  ],
  "keywords": [],
  "latitude": "0",
  "longitude": "0",
  "original_height": 1200,
  "original_size": 424855,
  "original_width": 1600,
  "title": ""
}
