{
  "altitude": 0,
  "caption": "",
  "date_time_original": [
    "2009-06-26T19:17:07+00:00"
  ],
  "date_time_uploaded": "2009-08-16T03:16:22+00:00",
  "filename": "Buchan8.jpg",
  "hidden": false,
  "image_key": "rqRcgj6",
  "images": [
    "rqRcgj6-Ti.jpg",
    "rqRcgj6-Th.jpg",
    "rqRcgj6-S.jpg",
    "rqRcgj6-M.jpg",
    "rqRcgj6-L.jpg",
    "rqRcgj6-XL.jpg",
    "rqRcgj6-X2.jpg",
    "rqRcgj6-X3.jpg",
    "rqRcgj6-Original.jpg"
  ],
  "keywords": [
    "Wilsons Cave EB4",
    "caving",
    "romina carfi",
    "buchan"
  ],
  "latitude": "0",
  "longitude": "0",
  "original_height": 2304,
  "original_size": 4647131,
  "original_width": 3072,
  "title": ""
}
