{
  "altitude": 0,
  "caption": "",
  "date_time_original": [
    "2008-04-12T22:26:12+00:00"
  ],
  "date_time_uploaded": "2008-05-17T06:21:01+00:00",
  "filename": "MtHowitt3.JPG",
  "hidden": false,
  "image_key": "8sNRFxb",
  "images": [
    "8sNRFxb-Ti.jpg",
    "8sNRFxb-Th.jpg",
    "8sNRFxb-S.jpg",
    "8sNRFxb-M.jpg",
    "8sNRFxb-L.jpg",
    "8sNRFxb-XL.jpg",
    "8sNRFxb-X2.jpg",
    "8sNRFxb-X3.jpg",
    "8sNRFxb-Original.jpg"
  ],
  "keywords": [],
  "latitude": "0",
  "longitude": "0",
  "original_height": 2736,
  "original_size": 2286432,
  "original_width": 3648,
  "title": ""
}
