{
  "altitude": 0,
  "caption": "",
  "date_time_original": [
    "2007-08-19T00:07:48+00:00"
  ],
  "date_time_uploaded": "2011-06-22T14:01:04+00:00",
  "filename": "185901350.JPG",
  "hidden": false,
  "image_key": "Tq4MWLk",
  "images": [
    "Tq4MWLk-Ti.jpg",
    "Tq4MWLk-Th.jpg",
    "Tq4MWLk-S.jpg",
    "Tq4MWLk-M.jpg",
    "Tq4MWLk-L.jpg",
    "Tq4MWLk-XL.jpg",
    "Tq4MWLk-X2.jpg",
    "Tq4MWLk-X3.jpg",
    "Tq4MWLk-Original.jpg"
  ],
  "keywords": [],
  "latitude": "0",
  "longitude": "0",
  "original_height": 2004,
  "original_size": 3314052,
  "original_width": 2760,
  "title": ""
}
