{
  "altitude": 0,
  "caption": "",
  "date_time_original": [
    "2006-09-16T21:59:45+00:00"
  ],
  "date_time_uploaded": "2006-10-07T03:10:33+00:00",
  "filename": "Wilsons Prom 033.jpg",
  "hidden": false,
  "image_key": "LdGrtKP",
  "images": [
    "LdGrtKP-Ti.jpg",
    "LdGrtKP-Th.jpg",
    "LdGrtKP-S.jpg",
    "LdGrtKP-M.jpg",
    "LdGrtKP-L.jpg",
    "LdGrtKP-XL.jpg",
    "LdGrtKP-X2.jpg",
    "LdGrtKP-X3.jpg",
    "LdGrtKP-Original.jpg"
  ],
  "keywords": [
    "wilsons prom",
    "sealers cove"
  ],
  "latitude": "-39.018127",
  "longitude": "146.434032",
  "original_height": 1280,
  "original_size": 783384,
  "original_width": 960,
  "title": ""
}
